environmentconf/__init__.py
environmentconf/envconf_manager.py
environmentconf/executors/__init__.py
environmentconf/executors/artifact_runner.py
environmentconf/executors/base.py
environmentconf/executors/executor_factory.py
environmentconf/executors/package_runner.py
environmentconf/executors/process_runner.py
environmentconf/resources/configurations.yaml
environmentconf/resources/environments.yaml
environmentconf/utils/__init__.py
environmentconf/utils/change_manager.py
environmentconf/utils/command_parser.py
environmentconf/utils/config_reader.py
environmentconf-0.8.dist-info/LICENSE.txt
environmentconf-0.8.dist-info/METADATA
environmentconf-0.8.dist-info/WHEEL
environmentconf-0.8.dist-info/top_level.txt
environmentconf-0.8.dist-info/RECORD
