Metadata-Version: 2.1
Name: environmentconf
Version: 0.8
Summary: Environment configurator for the distributed systems
Home-page: https://github.com/maulik887/environmentconf
Author: Maulik Patel
Author-email: maulik.info.tech@gmail.com
License: MIT
Download-URL: https://github.com/maulik887/environmentconf/archive/refs/tags/0.8.zip
Keywords: Environment,Configuration,Docker,EC2,Server
Platform: UNKNOWN
Classifier: Development Status :: 3 - Alpha
Classifier: Intended Audience :: Developers
Classifier: Topic :: Software Development :: Build Tools
Classifier: License :: OSI Approved :: MIT License
Classifier: Programming Language :: Python :: 3.6
Requires-Dist: jsonschema (>=3.2.0)
Requires-Dist: pyyaml (>=5.4.1)
